villaBackendSdk/__init__.py
villaBackendSdk/_nbdev.py
villaBackendSdk/basket.py
villaBackendSdk-0.0.1.dist-info/LICENSE
villaBackendSdk-0.0.1.dist-info/METADATA
villaBackendSdk-0.0.1.dist-info/WHEEL
villaBackendSdk-0.0.1.dist-info/entry_points.txt
villaBackendSdk-0.0.1.dist-info/top_level.txt
villaBackendSdk-0.0.1.dist-info/RECORD
