Metadata-Version: 2.1
Name: villaBackendSdk
Version: 0.0.1
Summary: interact with villa cart and ordering endpoints
Home-page: https://github.com/thanakijwanavit/pynamologger/tree/master/
Author: nic wanavit
Author-email: nwanavit@hatari.cc
License: Apache Software License 2.0
Keywords: villa cart orders basket
Platform: UNKNOWN
Classifier: Development Status :: 3 - Alpha
Classifier: Intended Audience :: Developers
Classifier: License :: OSI Approved :: Apache Software License
Classifier: Natural Language :: English
Classifier: Programming Language :: Python :: 3.6
Classifier: Programming Language :: Python :: 3.7
Classifier: Programming Language :: Python :: 3.8
Requires-Python: >=3.6
Requires-Dist: lambdasdk
Requires-Dist: awsSchema
Requires-Dist: nicHelper
